.gitignore
CHANGES.rst
LICENSE.rst
MANIFEST.in
README.rst
requirements.txt
setup.py
examples/activity.py
examples/authentication.py
plex.activity.py.egg-info/PKG-INFO
plex.activity.py.egg-info/SOURCES.txt
plex.activity.py.egg-info/dependency_links.txt
plex.activity.py.egg-info/requires.txt
plex.activity.py.egg-info/top_level.txt
plex_activity/__init__.py
plex_activity/activity.py
plex_activity/core/__init__.py
plex_activity/core/helpers.py
plex_activity/sources/__init__.py
plex_activity/sources/base.py
plex_activity/sources/s_logging/__init__.py
plex_activity/sources/s_logging/main.py
plex_activity/sources/s_logging/parsers/__init__.py
plex_activity/sources/s_logging/parsers/base.py
plex_activity/sources/s_logging/parsers/now_playing.py
plex_activity/sources/s_logging/parsers/scrobble.py
plex_activity/sources/s_websocket/__init__.py
plex_activity/sources/s_websocket/main.py