Metadata-Version: 1.1
Name: plex.activity.py
Version: 0.6.2
Summary: Real-time activity extension for plex.py
Home-page: https://github.com/fuzeman/plex.activity.py
Author: Dean Gardiner
Author-email: me@dgardiner.net
License: MIT
Platform: any
Classifier: Development Status :: 4 - Beta
Classifier: Intended Audience :: Developers
Classifier: Operating System :: OS Independent
Classifier: Programming Language :: Python
